schemas/frame_schema.json
schemas/level_schema.json
schemas/page_schema.json
schemas/series_schema.json
schemas/tiff_schema.json
tiffinspector/__init__.py
tiffinspector/_version.py
tiff_inspector-0.1.1.dist-info/LICENSE
tiff_inspector-0.1.1.dist-info/METADATA
tiff_inspector-0.1.1.dist-info/WHEEL
tiff_inspector-0.1.1.dist-info/top_level.txt
tiff_inspector-0.1.1.dist-info/RECORD
