Metadata-Version: 2.1
Name: tiff-inspector
Version: 0.1.1
Summary: A package for examining the structure and contents of the metadata contained within tiff files
Home-page: https://github.com/jason-weirather/tiff-inspector
Author: Jason L Weirather
Author-email: jason.weirather@gmail.com
Classifier: Development Status :: 3 - Alpha
Classifier: Intended Audience :: Developers
Classifier: License :: OSI Approved :: MIT License
Classifier: Operating System :: OS Independent
Classifier: Programming Language :: Python :: 3
Classifier: Programming Language :: Python :: 3.6
Classifier: Programming Language :: Python :: 3.7
Classifier: Programming Language :: Python :: 3.8
Classifier: Programming Language :: Python :: 3.9
Requires-Python: >=3.6
License-File: LICENSE
Requires-Dist: tifffile (>=2021.1.1)
Requires-Dist: imagecodecs
Requires-Dist: ipython
Requires-Dist: importlib-metadata ; python_version < "3.8"
